{
  "_meta": {
    "generated": "2026-03-28T16:33:34.142182",
    "radius_walk": 500,
    "radius_car": 1500
  },
  "Дубно КІНО": {
    "peak": 0,
    "morning": 0,
    "evening": 0,
    "weekend": 0,
    "walk_radius": 500,
    "car_radius": 1500,
    "walk_places_count": 0,
    "car_places_count": 0,
    "heatmap_points": [],
    "collected_at": "2026-03-28T16:33:43.116055"
  },
  "Дубно ЛІТАЧОК": {
    "peak": 0,
    "morning": 0,
    "evening": 0,
    "weekend": 0,
    "walk_radius": 500,
    "car_radius": 1500,
    "walk_places_count": 0,
    "car_places_count": 0,
    "heatmap_points": [],
    "collected_at": "2026-03-28T16:33:51.440447"
  }
}